MANIFEST.in
setup.cfg
setup.py
conf/e2transmission.json
conf/local.json
e2transmission/__init__.py
e2transmission/__main__.py
e2transmission/daemon.py
e2transmission/e_parser.py
e2transmission/transmission_rpc.py
e2transmission.egg-info/PKG-INFO
e2transmission.egg-info/SOURCES.txt
e2transmission.egg-info/dependency_links.txt
e2transmission.egg-info/entry_points.txt
e2transmission.egg-info/top_level.txt