Metadata-Version: 1.1
Name: e2transmission
Version: 1.0.0
Summary: add torrents from email to transmission
Home-page: https://github.com/harlov/e2transmission
Author: Nikita Harlov
Author-email: nikita@harlov.com
License: MTI License
Download-URL: https://github.com/harlov/e2transmission/archive/v1.0.0.tar.gz
Platform: UNKNOWN
Classifier: Environment :: Console
Classifier: Intended Audience :: End Users/Desktop
Classifier: License :: OSI Approved :: MIT License
Classifier: Operating System :: OS Independent
Classifier: Programming Language :: Python
Classifier: Programming Language :: Python :: 2.7
Classifier: Programming Language :: Python :: 3
Classifier: Programming Language :: Python :: 3.2
Classifier: Programming Language :: Python :: 3.3
Classifier: Programming Language :: Python :: 3.4
Classifier: Topic :: Communications :: Email
